rotafy/__init__.py
rotafy/api/manager.py
rotafy/api/notifier.py
rotafy/cli.py
rotafy/config/__init__.py
rotafy/config/chore.py
rotafy/config/config.py
rotafy/config/person.py
rotafy/rota/__init__.py
rotafy/rota/assignment.py
rotafy/rota/printable.py
rotafy/rota/rota.py
rotafy/rota/row.py
rotafy-0.1.0.dist-info/LICENSE
rotafy-0.1.0.dist-info/WHEEL
rotafy-0.1.0.dist-info/entry_points.txt
rotafy-0.1.0.dist-info/METADATA
rotafy-0.1.0.dist-info/RECORD
